Afine.py
__init__.py
test.py
Afine-0.0.2.dist-info/LICENSE
Afine-0.0.2.dist-info/METADATA
Afine-0.0.2.dist-info/WHEEL
Afine-0.0.2.dist-info/top_level.txt
Afine-0.0.2.dist-info/RECORD
