Metadata-Version: 2.2
Name: Afine
Version: 0.0.2
Summary: Afine is a gradient based PyTorch optimizer. 
Author-email: Psyche Halo <Psyche@WinsGod.com>
Project-URL: Homepage, https://github.com/PsycheHalo/Afine
Project-URL: Issues, https://github.com/PsycheHalo/Afine/issues
Keywords: affine,Afine,PyTorch,optimizer,AI,neural,NN
Classifier: Programming Language :: Python :: 3
Classifier: Operating System :: OS Independent
Requires-Python: >=3.8
License-File: LICENSE
Requires-Dist: torch>=1.7.0
